Workbook
Name Slicer_Supplier: #N/A

Sheet Sheet1
B3: INVENTORY LIST | F3: DASHBOARD
B6: Product ID | C6: Product name | D6: Category | E6: Supplier | F6: Cost | G6: Selling price | H6: Sales | I6: Quantity | J6: Reorder | K6: Lead time | L6: Hold % | M6: Revenue | N6: Profit per unit | O6: Total profit | P6: Profit margins% | Q6: Inventory value | R6: Months of stock | S6: Stock status | T6: dead stock | U6: Holding cost | V6: Inventory turnover (by month) | W6: Movement type
B7: P01 | C7: wireless mouse | D7: electronics | E7: supplier A | F7: 500 | G7: 800 | H7: 50 | I7: 200 | J7: 100 | K7: 7 | L7: 15 | M7: =Sheet1!$G7*Sheet1!$H7 -> 40000 | N7: =Sheet1!$G7-Sheet1!$F7 -> 300 | O7: =Sheet1!$N7*Sheet1!$H7 -> 15000 | P7: =Sheet1!$O7/Sheet1!$M7*100 -> 37.5 | Q7: =Sheet1!$F7*Sheet1!$I7 -> 100000 | R7: =Sheet1!$I7/Sheet1!$H7 -> 4 | S7: {=IF(I7:I19>J7:J19,"ok","Restock")} -> ok | T7: =IF(Sheet1!$R7>6,"dead", "Active") -> Active | U7: =Sheet1!$Q7*Sheet1!$L7/100 -> 15000 | V7: =Sheet1!$H7/Sheet1!$I7 -> 0.25 | W7: {=IF(V7:V21>0.5,"Fast",IF(V7:V21>0.2,"Normal","Slow"))} -> Normal
B8: P02 | C8: keyboard | D8: electronics | E8: supplier B | F8: 700 | G8: 1000 | H8: 40 | I8: 150 | J8: 80 | K8: 10 | L8: 15 | M8: =Sheet1!$G8*Sheet1!$H8 -> 40000 | N8: =Sheet1!$G8-Sheet1!$F8 -> 300 | O8: =Sheet1!$N8*Sheet1!$H8 -> 12000 | P8: =Sheet1!$O8/Sheet1!$M8*100 -> 30 | Q8: =Sheet1!$F8*Sheet1!$I8 -> 105000 | R8: =Sheet1!$I8/Sheet1!$H8 -> 3.75 | S8: ok | T8: =IF(Sheet1!$R8>6,"dead", "Active") -> Active | U8: =Sheet1!$Q8*Sheet1!$L8/100 -> 15750 | V8: =Sheet1!$H8/Sheet1!$I8 -> 0.26666667 | W8: Normal
B9: P03 | C9: notebook | D9: stationary | E9: supplier C | F9: 50 | G9: 120 | H9: 200 | I9: 500 | J9: 200 | K9: 5 | L9: 10 | M9: =Sheet1!$G9*Sheet1!$H9 -> 24000 | N9: =Sheet1!$G9-Sheet1!$F9 -> 70 | O9: =Sheet1!$N9*Sheet1!$H9 -> 14000 | P9: =Sheet1!$O9/Sheet1!$M9*100 -> 58.333333 | Q9: =Sheet1!$F9*Sheet1!$I9 -> 25000 | R9: =Sheet1!$I9/Sheet1!$H9 -> 2.5 | S9: ok | T9: =IF(Sheet1!$R9>6,"dead", "Active") -> Active | U9: =Sheet1!$Q9*Sheet1!$L9/100 -> 2500 | V9: =Sheet1!$H9/Sheet1!$I9 -> 0.4 | W9: Normal
B10: P04 | C10: pen pack | D10: stationary | E10: supplier C | F10: 20 | G10: 60 | H10: 300 | I10: 1000 | J10: 300 | K10: 5 | L10: 10 | M10: =Sheet1!$G10*Sheet1!$H10 -> 18000 | N10: =Sheet1!$G10-Sheet1!$F10 -> 40 | O10: =Sheet1!$N10*Sheet1!$H10 -> 12000 | P10: =Sheet1!$O10/Sheet1!$M10*100 -> 66.666667 | Q10: =Sheet1!$F10*Sheet1!$I10 -> 20000 | R10: =Sheet1!$I10/Sheet1!$H10 -> 3.3333333 | S10: ok | T10: =IF(Sheet1!$R10>6,"dead", "Active") -> Active | U10: =Sheet1!$Q10*Sheet1!$L10/100 -> 2000 | V10: =Sheet1!$H10/Sheet1!$I10 -> 0.3 | W10: Normal
B11: P05 | C11: office chair | D11: furniture | E11: supplier D | F11: 3000 | G11: 5000 | H11: 10 | I11: 50 | J11: 20 | K11: 15 | L11: 20 | M11: =Sheet1!$G11*Sheet1!$H11 -> 50000 | N11: =Sheet1!$G11-Sheet1!$F11 -> 2000 | O11: =Sheet1!$N11*Sheet1!$H11 -> 20000 | P11: =Sheet1!$O11/Sheet1!$M11*100 -> 40 | Q11: =Sheet1!$F11*Sheet1!$I11 -> 150000 | R11: =Sheet1!$I11/Sheet1!$H11 -> 5 | S11: ok | T11: =IF(Sheet1!$R11>6,"dead", "Active") -> Active | U11: =Sheet1!$Q11*Sheet1!$L11/100 -> 30000 | V11: =Sheet1!$H11/Sheet1!$I11 -> 0.2 | W11: Slow
B12: P06 | C12: webcam | D12: electronics | E12: supplier A | F12: 450 | G12: 850 | H12: 30 | I12: 100 | J12: 60 | K12: 7 | L12: 10 | M12: =Sheet1!$G12*Sheet1!$H12 -> 25500 | N12: =Sheet1!$G12-Sheet1!$F12 -> 400 | O12: =Sheet1!$N12*Sheet1!$H12 -> 12000 | P12: =Sheet1!$O12/Sheet1!$M12*100 -> 47.058824 | Q12: =Sheet1!$F12*Sheet1!$I12 -> 45000 | R12: =Sheet1!$I12/Sheet1!$H12 -> 3.3333333 | S12: ok | T12: =IF(Sheet1!$R12>6,"dead", "Active") -> Active | U12: =Sheet1!$Q12*Sheet1!$L12/100 -> 4500 | V12: =Sheet1!$H12/Sheet1!$I12 -> 0.3 | W12: Normal
B13: P07 | C13: flash drive | D13: electronics | E13: supplier B | F13: 100 | G13: 150 | H13: 100 | I13: 250 | J13: 250 | K13: 10 | L13: 16 | M13: =Sheet1!$G13*Sheet1!$H13 -> 15000 | N13: =Sheet1!$G13-Sheet1!$F13 -> 50 | O13: =Sheet1!$N13*Sheet1!$H13 -> 5000 | P13: =Sheet1!$O13/Sheet1!$M13*100 -> 33.333333 | Q13: =Sheet1!$F13*Sheet1!$I13 -> 25000 | R13: =Sheet1!$I13/Sheet1!$H13 -> 2.5 | S13: Restock | T13: =IF(Sheet1!$R13>6,"dead", "Active") -> Active | U13: =Sheet1!$Q13*Sheet1!$L13/100 -> 4000 | V13: =Sheet1!$H13/Sheet1!$I13 -> 0.4 | W13: Normal
B14: P08 | C14: hard disk | D14: electronics | E14: supplier A | F14: 600 | G14: 660 | H14: 250 | I14: 700 | J14: 500 | K14: 7 | L14: 10 | M14: =Sheet1!$G14*Sheet1!$H14 -> 165000 | N14: =Sheet1!$G14-Sheet1!$F14 -> 60 | O14: =Sheet1!$N14*Sheet1!$H14 -> 15000 | P14: =Sheet1!$O14/Sheet1!$M14*100 -> 9.0909091 | Q14: =Sheet1!$F14*Sheet1!$I14 -> 420000 | R14: =Sheet1!$I14/Sheet1!$H14 -> 2.8 | S14: ok | T14: =IF(Sheet1!$R14>6,"dead", "Active") -> Active | U14: =Sheet1!$Q14*Sheet1!$L14/100 -> 42000 | V14: =Sheet1!$H14/Sheet1!$I14 -> 0.35714286 | W14: Normal
B15: P09 | C15: monitor | D15: electronics | E15: supplier C | F15: 5000 | G15: 7000 | H15: 20 | I15: 80 | J15: 20 | K15: 5 | L15: 20 | M15: =Sheet1!$G15*Sheet1!$H15 -> 140000 | N15: =Sheet1!$G15-Sheet1!$F15 -> 2000 | O15: =Sheet1!$N15*Sheet1!$H15 -> 40000 | P15: =Sheet1!$O15/Sheet1!$M15*100 -> 28.571429 | Q15: =Sheet1!$F15*Sheet1!$I15 -> 400000 | R15: =Sheet1!$I15/Sheet1!$H15 -> 4 | S15: ok | T15: =IF(Sheet1!$R15>6,"dead", "Active") -> Active | U15: =Sheet1!$Q15*Sheet1!$L15/100 -> 80000 | V15: =Sheet1!$H15/Sheet1!$I15 -> 0.25 | W15: Normal
B16: P10 | C16: smartphones | D16: electronics | E16: supplier D | F16: 10000 | G16: 15000 | H16: 250 | I16: 550 | J16: 250 | K16: 15 | L16: 30 | M16: =Sheet1!$G16*Sheet1!$H16 -> 3750000 | N16: =Sheet1!$G16-Sheet1!$F16 -> 5000 | O16: =Sheet1!$N16*Sheet1!$H16 -> 1250000 | P16: =Sheet1!$O16/Sheet1!$M16*100 -> 33.333333 | Q16: =Sheet1!$F16*Sheet1!$I16 -> 5500000 | R16: =Sheet1!$I16/Sheet1!$H16 -> 2.2 | S16: ok | T16: =IF(Sheet1!$R16>6,"dead", "Active") -> Active | U16: =Sheet1!$Q16*Sheet1!$L16/100 -> 1650000 | V16: =Sheet1!$H16/Sheet1!$I16 -> 0.45454545 | W16: Normal
B17: P11 | C17: cables | D17: electronics | E17: supplier E | F17: 150 | G17: 200 | H17: 500 | I17: 900 | J17: 700 | K17: 6 | L17: 8 | M17: =Sheet1!$G17*Sheet1!$H17 -> 100000 | N17: =Sheet1!$G17-Sheet1!$F17 -> 50 | O17: =Sheet1!$N17*Sheet1!$H17 -> 25000 | P17: =Sheet1!$O17/Sheet1!$M17*100 -> 25 | Q17: =Sheet1!$F17*Sheet1!$I17 -> 135000 | R17: =Sheet1!$I17/Sheet1!$H17 -> 1.8 | S17: ok | T17: =IF(Sheet1!$R17>6,"dead", "Active") -> Active | U17: =Sheet1!$Q17*Sheet1!$L17/100 -> 10800 | V17: =Sheet1!$H17/Sheet1!$I17 -> 0.55555556 | W17: Fast
B18: P12 | C18: motherboard | D18: electronics | E18: supplier E | F18: 750 | G18: 900 | H18: 40 | I18: 200 | J18: 70 | K18: 6 | L18: 14 | M18: =Sheet1!$G18*Sheet1!$H18 -> 36000 | N18: =Sheet1!$G18-Sheet1!$F18 -> 150 | O18: =Sheet1!$N18*Sheet1!$H18 -> 6000 | P18: =Sheet1!$O18/Sheet1!$M18*100 -> 16.666667 | Q18: =Sheet1!$F18*Sheet1!$I18 -> 150000 | R18: =Sheet1!$I18/Sheet1!$H18 -> 5 | S18: ok | T18: =IF(Sheet1!$R18>6,"dead", "Active") -> Active | U18: =Sheet1!$Q18*Sheet1!$L18/100 -> 21000 | V18: =Sheet1!$H18/Sheet1!$I18 -> 0.2 | W18: Slow
B19: P13 | C19: cpu | D19: electronics | E19: supplier F | F19: 15000 | G19: 20000 | H19: 25 | I19: 140 | J19: 250 | K19: 4 | L19: 24 | M19: =Sheet1!$G19*Sheet1!$H19 -> 500000 | N19: =Sheet1!$G19-Sheet1!$F19 -> 5000 | O19: =Sheet1!$N19*Sheet1!$H19 -> 125000 | P19: =Sheet1!$O19/Sheet1!$M19*100 -> 25 | Q19: =Sheet1!$F19*Sheet1!$I19 -> 2100000 | R19: =Sheet1!$I19/Sheet1!$H19 -> 5.6 | S19: Restock | T19: =IF(Sheet1!$R19>6,"dead", "Active") -> Active | U19: =Sheet1!$Q19*Sheet1!$L19/100 -> 504000 | V19: =Sheet1!$H19/Sheet1!$I19 -> 0.17857143 | W19: Slow
B20: P14 | C20: screen protector | D20: electronics | E20: supplier F | F20: 50 | G20: 90 | H20: 0 | I20: 10 | J20: 1000 | K20: 4 | L20: 10 | M20: =Sheet1!$G20*Sheet1!$H20 -> 0 | N20: =Sheet1!$G20-Sheet1!$F20 -> 40 | O20: =Sheet1!$N20*Sheet1!$H20 -> 0 | P20: 0 | Q20: =Sheet1!$F20*Sheet1!$I20 -> 500 | R20: 10 | S20: dead | T20: =IF(Sheet1!$R20>6,"dead", "Active") -> dead | U20: =Sheet1!$Q20*Sheet1!$L20/100 -> 50 | V20: =Sheet1!$H20/Sheet1!$I20 -> 0 | W20: Slow
B21: P15 | C21: gaming desk | D21: furniture | E21: supplier F | F21: 7000 | G21: 9000 | H21: 15 | I21: 60 | J21: 35 | K21: 4 | L21: 30 | M21: =Sheet1!$G21*Sheet1!$H21 -> 135000 | N21: =Sheet1!$G21-Sheet1!$F21 -> 2000 | O21: =Sheet1!$N21*Sheet1!$H21 -> 30000 | P21: =Sheet1!$O21/Sheet1!$M21*100 -> 22.222222 | Q21: =Sheet1!$F21*Sheet1!$I21 -> 420000 | R21: =Sheet1!$I21/Sheet1!$H21 -> 4 | S21: ok | T21: =IF(Sheet1!$R21>6,"dead", "Active") -> Active | U21: =Sheet1!$Q21*Sheet1!$L21/100 -> 126000 | V21: =Sheet1!$H21/Sheet1!$I21 -> 0.25 | W21: Normal

Sheet DASHBOARD
C2: Inventory profitability & Operations Dashboard
C4: 5038500 | E4: 1581000 | G4: 0.3152 | I4: 9595500 | K4: 500
C5: Total Revenue | E5: Total Profit | G5: Avg Profit Margin | I5: Inventory value | K5: Dead Stock Value
B40: Key Trends & Insights:
B41: • Smartphones and CPUs are highly performing in overall profit with a profit margin of 33% and 25%.
B42: • Whereas, 3 low cost products pen pack, notebook and webcam has high profit margin, chances of pricing efficiency.
B43: • Supplier D contribute the most based on profit but taking 15 days in lead time.
B44: • ₹500 is stuck in dead stock, along with that 3 products can be danger. (screen protector, hard disk, motherboard)
B45: • Electronic items got more revenue but with low profit accordingly, while stationary items has good ratio between revenue and profit.
B47: Recommendations:
B48: • Certain products are stuck in inventory, which leads to a fall in profitability.
B49: • Supplier D driving high profit but has 15 days lead time, should be improved for inventory benefits.
B50: • Furniture products has high revenue but in terms of profit they are lacking, optimizing this can give rapid growth.
B51: • Some products are more costly with average profit margin, measures in holding cost could be profitable.

Sheet Analysis
A3: Products name | B3: Sum of Total profit
A4: pen pack | B4: 12000
A5: notebook | B5: 14000
A6: wireless mouse | B6: 15000
A7: hard disk | B7: 15000
A8: office chair | B8: 20000
A9: cables | B9: 25000
A10: gaming desk | B10: 30000
A11: monitor | B11: 40000
A12: cpu | B12: 125000
A13: smartphones | B13: 1250000
A14: Grand Total | B14: 1546000

Sheet Supplier_analysis
A3: Suppliers | B3: Total profit | C3: Inventory value | D3: Average Lead time
A4: supplier A | B4: 42000 | C4: 565000 | D4: 7
A5: supplier B | B5: 17000 | C5: 130000 | D5: 10
A6: supplier C | B6: 66000 | C6: 445000 | D6: 5
A7: supplier D | B7: 1270000 | C7: 5650000 | D7: 15
A8: supplier E | B8: 31000 | C8: 285000 | D8: 6
A9: supplier F | B9: 155000 | C9: 2520500 | D9: 4
A10: Grand Total | B10: 1581000 | C10: 9595500 | D10: 7.3333333

Sheet Dead_stock
A7: Dstock Status | B7: Stock ratio
A8: Active | B8: 14
A9: dead | B9: 1
A10: Grand Total | B10: 15

Sheet Category_analysis
A3: Category | B3: Revenue | C3: Total profit
A4: electronics | B4: 4811500 | C4: 1505000
A5: furniture | B5: 185000 | C5: 50000
A6: stationary | B6: 42000 | C6: 26000
A7: Grand Total | B7: 5038500 | C7: 1581000

Sheet RAW
A3: Row Labels | B3: Total profit | D3: Product ID | E3: Product | F3: Total profit | G3: Inventory value | H3: Profit margin% | I3: cost per unit | J3: profit per unit | K3: Average margin | L3: Average cost | N3: vert
A4: supplier A | B4: 42000 | D4: P01 | E4: wireless mouse | F4: {=VLOOKUP(RAW!D4,Sheet1!B6:Q21,{14,16},0)} -> 15000 | G4: 100000 | H4: {=VLOOKUP(D4,Sheet1!B6:P21,{15},0)} -> 37.5 | I4: {=VLOOKUP(D4,Sheet1!B6:N21,{5,13},0)} -> 500 | J4: 300 | K4: =AVERAGE(H4:H18) -> 31.518448 | L4: =AVERAGE(I4:I18) -> 2891.3333 | N4: X | O4: Y
A5: supplier B | B5: 17000 | D5: P02 | E5: keyboard | F5: {=VLOOKUP(RAW!D5,Sheet1!B7:Q22,{14,16},0)} -> 12000 | G5: 105000 | H5: {=VLOOKUP(D5,Sheet1!B7:P22,{15},0)} -> 30 | I5: {=VLOOKUP(D5,Sheet1!B7:N22,{5,13},0)} -> 700 | J5: 300 | N5: =MEDIAN(I4:I18) -> 600 | O5: 0
A6: supplier C | B6: 66000 | D6: P03 | E6: notebook | F6: {=VLOOKUP(RAW!D6,Sheet1!B8:Q23,{14,16},0)} -> 14000 | G6: 25000 | H6: {=VLOOKUP(D6,Sheet1!B8:P23,{15},0)} -> 58.333333 | I6: {=VLOOKUP(D6,Sheet1!B8:N23,{5,13},0)} -> 50 | J6: 70 | N6: 600 | O6: =MAX(H4:H18) -> 66.666667
A7: supplier D | B7: 1270000 | D7: P04 | E7: pen pack | F7: {=VLOOKUP(RAW!D7,Sheet1!B9:Q24,{14,16},0)} -> 12000 | G7: 20000 | H7: {=VLOOKUP(D7,Sheet1!B9:P24,{15},0)} -> 66.666667 | I7: {=VLOOKUP(D7,Sheet1!B9:N24,{5,13},0)} -> 20 | J7: 40
A8: supplier E | B8: 31000 | D8: P05 | E8: office chair | F8: {=VLOOKUP(RAW!D8,Sheet1!B10:Q25,{14,16},0)} -> 20000 | G8: 150000 | H8: {=VLOOKUP(D8,Sheet1!B10:P25,{15},0)} -> 40 | I8: {=VLOOKUP(D8,Sheet1!B10:N25,{5,13},0)} -> 3000 | J8: 2000 | N8: horz
A9: supplier F | B9: 155000 | D9: P06 | E9: webcam | F9: {=VLOOKUP(RAW!D9,Sheet1!B11:Q26,{14,16},0)} -> 12000 | G9: 45000 | H9: {=VLOOKUP(D9,Sheet1!B11:P26,{15},0)} -> 47.058824 | I9: {=VLOOKUP(D9,Sheet1!B11:N26,{5,13},0)} -> 450 | J9: 400 | N9: X | O9: Y
A10: Grand Total | B10: 1581000 | D10: P07 | E10: flash drive | F10: {=VLOOKUP(RAW!D10,Sheet1!B12:Q27,{14,16},0)} -> 5000 | G10: 25000 | H10: {=VLOOKUP(D10,Sheet1!B12:P27,{15},0)} -> 33.333333 | I10: {=VLOOKUP(D10,Sheet1!B12:N27,{5,13},0)} -> 100 | J10: 50 | N10: 0 | O10: 31.52
D11: P08 | E11: hard disk | F11: {=VLOOKUP(RAW!D11,Sheet1!B13:Q28,{14,16},0)} -> 15000 | G11: 420000 | H11: {=VLOOKUP(D11,Sheet1!B13:P28,{15},0)} -> 9.0909091 | I11: {=VLOOKUP(D11,Sheet1!B13:N28,{5,13},0)} -> 600 | J11: 60 | N11: =MAX(I4:I18) -> 15000 | O11: 31.52
D12: P09 | E12: monitor | F12: {=VLOOKUP(RAW!D12,Sheet1!B14:Q29,{14,16},0)} -> 40000 | G12: 400000 | H12: {=VLOOKUP(D12,Sheet1!B14:P29,{15},0)} -> 28.571429 | I12: {=VLOOKUP(D12,Sheet1!B14:N29,{5,13},0)} -> 5000 | J12: 2000
D13: P10 | E13: smartphones | F13: {=VLOOKUP(RAW!D13,Sheet1!B15:Q30,{14,16},0)} -> 1250000 | G13: 5500000 | H13: {=VLOOKUP(D13,Sheet1!B15:P30,{15},0)} -> 33.333333 | I13: {=VLOOKUP(D13,Sheet1!B15:N30,{5,13},0)} -> 10000 | J13: 5000
D14: P11 | E14: cables | F14: {=VLOOKUP(RAW!D14,Sheet1!B16:Q31,{14,16},0)} -> 25000 | G14: 135000 | H14: {=VLOOKUP(D14,Sheet1!B16:P31,{15},0)} -> 25 | I14: {=VLOOKUP(D14,Sheet1!B16:N31,{5,13},0)} -> 150 | J14: 50
D15: P12 | E15: motherboard | F15: {=VLOOKUP(RAW!D15,Sheet1!B17:Q32,{14,16},0)} -> 6000 | G15: 150000 | H15: {=VLOOKUP(D15,Sheet1!B17:P32,{15},0)} -> 16.666667 | I15: {=VLOOKUP(D15,Sheet1!B17:N32,{5,13},0)} -> 750 | J15: 150
D16: P13 | E16: Cpu | F16: 125000 | G16: 2100000 | H16: {=VLOOKUP(D16,Sheet1!B18:P33,{15},0)} -> 25 | I16: 15000 | J16: 5000
D17: P14 | E17: screen protector | F17: {=VLOOKUP(RAW!D17,Sheet1!B19:Q34,{14,16},0)} -> 0 | G17: 500 | H17: {=VLOOKUP(D17,Sheet1!B19:P34,{15},0)} -> 0 | I17: {=VLOOKUP(D17,Sheet1!B19:N34,{5,13},0)} -> 50 | J17: 40
D18: P15 | E18: gaming desk | F18: {=VLOOKUP(RAW!D18,Sheet1!B20:Q35,{14,16},0)} -> 30000 | G18: 420000 | H18: {=VLOOKUP(D18,Sheet1!B20:P35,{15},0)} -> 22.222222 | I18: {=VLOOKUP(D18,Sheet1!B20:N35,{5,13},0)} -> 7000 | J18: 2000
